itu/__init__.py
itu-0.1.0.dist-info/LICENSE
itu-0.1.0.dist-info/METADATA
itu-0.1.0.dist-info/WHEEL
itu-0.1.0.dist-info/top_level.txt
itu-0.1.0.dist-info/RECORD
