Metadata-Version: 2.1
Name: itu
Version: 0.1.0
Summary: Indonesia version of import this.
Home-page: http://github.com/ismailsunni/itu
Author: Ismail Sunni
Author-email: imajimatika@gmail.com
License: MIT
Platform: UNKNOWN
Classifier: Programming Language :: Python
Classifier: License :: OSI Approved :: MIT License
Classifier: Operating System :: OS Independent
Classifier: Topic :: Education
